ntlm_auth/U32.py
ntlm_auth/__init__.py
ntlm_auth/compute_hash.py
ntlm_auth/compute_keys.py
ntlm_auth/compute_response.py
ntlm_auth/constants.py
ntlm_auth/des.py
ntlm_auth/des_c.py
ntlm_auth/des_data.py
ntlm_auth/gss_channel_bindings.py
ntlm_auth/messages.py
ntlm_auth/ntlm.py
ntlm_auth/rc4.py
ntlm_auth/session_security.py
ntlm_auth/target_info.py
pivot_suite/__init__.py
pivot_suite/__main__.py
pivot_suite/client.py
pivot_suite/pivotsuite.py
pivot_suite/server.py
pivot_suite/six.py
pivot_suite/version.py
PivotSuite-1.1.dist-info/LICENSE.md
PivotSuite-1.1.dist-info/METADATA
PivotSuite-1.1.dist-info/WHEEL
PivotSuite-1.1.dist-info/entry_points.txt
PivotSuite-1.1.dist-info/top_level.txt
PivotSuite-1.1.dist-info/RECORD
